.gitignore
.travis.yml
MANIFEST.in
README.md
setup.cfg
setup.py
tox.ini
docs/vydia.gif
vydia/__init__.py
vydia/main.py
vydia.egg-info/PKG-INFO
vydia.egg-info/PKG-INFO.sync-conflict-20171111-161719-AYCE34L
vydia.egg-info/SOURCES.txt
vydia.egg-info/dependency_links.txt
vydia.egg-info/entry_points.txt
vydia.egg-info/requires.sync-conflict-20171111-161718-AYCE34L.txt
vydia.egg-info/requires.txt
vydia.egg-info/top_level.txt
vydia/core/__init__.py
vydia/core/controller.py
vydia/core/model.py
vydia/core/view.py
vydia/extra/__init__.py
vydia/extra/macos_mpv_wrapper.py
vydia/extra/player.py
vydia/extra/plugins.py
vydia/extra/utils.py
vydia/tests/__init__.py
vydia/tests/test_model.py