Metadata-Version: 1.1
Name: vydia
Version: 0.6.3
Summary: A modularized video player with resume function
Home-page: https://github.com/kpj/Vydia
Author: kpj
Author-email: kpjkpjkpjkpjkpjkpj@gmail.com
License: MIT
Keywords: vydia video playback
Platform: UNKNOWN
Classifier: Development Status :: 3 - Alpha
Classifier: Intended Audience :: End Users/Desktop
Classifier: Topic :: Multimedia :: Video :: Display
Classifier: License :: OSI Approved :: MIT License
Classifier: Programming Language :: Python :: 3 :: Only
